futures_actors/__init__.py
futures_actors/_base_actor.py
futures_actors/process_actor.py
futures_actors/tests.py
futures_actors/thread_actor.py
futures_actors-0.0.5.dist-info/DESCRIPTION.rst
futures_actors-0.0.5.dist-info/METADATA
futures_actors-0.0.5.dist-info/RECORD
futures_actors-0.0.5.dist-info/WHEEL
futures_actors-0.0.5.dist-info/metadata.json
futures_actors-0.0.5.dist-info/top_level.txt
