Metadata-Version: 2.0
Name: futures-actors
Version: 0.0.5
Summary: An extension of the concurrent.futures module to support stateful computations.
Home-page: https://github.com/Erotemic/futures_actors
Author: Jon Crall
Author-email: erotemic@gmail.com
License: Apache 2
Platform: UNKNOWN
Classifier: Development Status :: 3 - Alpha
Classifier: Intended Audience :: Developers
Classifier: Topic :: Software Development :: Libraries :: Python Modules
Classifier: License :: OSI Approved :: Apache Software License
Classifier: Programming Language :: Python :: 2.7
Classifier: Programming Language :: Python :: 3
Requires-Dist: ubelt
